.coveragerc
.editorconfig
.gitignore
.travis.yml
LICENSE
README.md
pyproject.toml
requirements.txt
requirements_dev.txt
setup.cfg
setup.py
.github/workflows/python-publish.yml
democritus_stats/__init__.py
democritus_stats/stats.py
democritus_stats.egg-info/PKG-INFO
democritus_stats.egg-info/SOURCES.txt
democritus_stats.egg-info/dependency_links.txt
democritus_stats.egg-info/requires.txt
democritus_stats.egg-info/top_level.txt
democritus_stats.egg-info/zip-safe
tests/__init__.py
tests/test_stats.py